diannpy/__init__.py
diannpy/handlers.py
diannpy/operation.py
diannpy-0.1.1.dist-info/METADATA
diannpy-0.1.1.dist-info/WHEEL
diannpy-0.1.1.dist-info/RECORD
