Metadata-Version: 2.1
Name: diannpy
Version: 0.1.1
Summary: a package to provide additional report from DIANN's output of proteomics experiment
Author: Toan Phung
Author-email: toan.phungkhoiquoctoan@gmail.com
Requires-Python: >=3.9,<4.0
Classifier: Programming Language :: Python :: 3
Classifier: Programming Language :: Python :: 3.9
Classifier: Programming Language :: Python :: 3.10
Classifier: Programming Language :: Python :: 3.11
Requires-Dist: goatools (>=1.2.3,<2.0.0)
Requires-Dist: matplotlib (>=3.5.3,<4.0.0)
Requires-Dist: missingpy (>=0.2.0,<0.3.0)
Requires-Dist: pandas (==2.0.0)
Requires-Dist: pandera (>=0.12.0,<0.13.0)
Requires-Dist: plotnine (>=0.12.1,<0.13.0)
Requires-Dist: requests (>=2.30.0,<3.0.0)
Requires-Dist: scikit-learn (==1.1.2)
Requires-Dist: seaborn (>=0.12.0,<0.13.0)
Requires-Dist: sequal (>=1.0.1,<2.0.0)
Requires-Dist: tornado (>=6.3.1,<7.0.0)
Requires-Dist: unimod-mapper (>=0.6.6,<0.7.0)
Requires-Dist: uniprotparser (>=1.1.0,<2.0.0)
